<?xml version="1.0" encoding="UTF-8"?>
<configuration>
    <!-- 定义日志文件路径 -->
    <property name="LOG_PATH" value="/apphome/logs"/>
    <property name="LOG_FILE" value="dhs-crm"/>

    <!-- 控制台输出格式 -->
    <appender name="CONSOLE" class="ch.qos.logback.core.ConsoleAppender">
        <encoder>
            <pattern>%d{yyyy-MM-dd HH:mm:ss.SSS} [%thread] %-5level %logger{36} - %msg%n</pattern>
            <charset>UTF-8</charset>
        </encoder>
    </appender>

    <!-- 文件输出格式 -->
    <appender name="FILE" class="ch.qos.logback.core.rolling.RollingFileAppender">
        <file>${LOG_PATH}/${LOG_FILE}.log</file>
        <encoder>
            <pattern>%d{yyyy-MM-dd HH:mm:ss.SSS} [%thread] %-5level %logger{50} - %msg%n</pattern>
            <charset>UTF-8</charset>
        </encoder>
        <rollingPolicy class="ch.qos.logback.core.rolling.TimeBasedRollingPolicy">
            <fileNamePattern>${LOG_PATH}/${LOG_FILE}-%d{yyyy-MM-dd}.%i.log</fileNamePattern>
            <timeBasedFileNamingAndTriggeringPolicy class="ch.qos.logback.core.rolling.SizeAndTimeBasedFNATP">
                <maxFileSize>100MB</maxFileSize>
            </timeBasedFileNamingAndTriggeringPolicy>
            <maxHistory>30</maxHistory>
        </rollingPolicy>
    </appender>

    <!-- 错误日志单独输出 -->
    <appender name="ERROR_FILE" class="ch.qos.logback.core.rolling.RollingFileAppender">
        <file>${LOG_PATH}/${LOG_FILE}-error.log</file>
        <filter class="ch.qos.logback.classic.filter.LevelFilter">
            <level>ERROR</level>
            <onMatch>ACCEPT</onMatch>
            <onMismatch>DENY</onMismatch>
        </filter>
        <encoder>
            <pattern>%d{yyyy-MM-dd HH:mm:ss.SSS} [%thread] %-5level %logger{50} - %msg%n</pattern>
            <charset>UTF-8</charset>
        </encoder>
        <rollingPolicy class="ch.qos.logback.core.rolling.TimeBasedRollingPolicy">
            <fileNamePattern>${LOG_PATH}/${LOG_FILE}-error-%d{yyyy-MM-dd}.%i.log</fileNamePattern>
            <timeBasedFileNamingAndTriggeringPolicy class="ch.qos.logback.core.rolling.SizeAndTimeBasedFNATP">
                <maxFileSize>50MB</maxFileSize>
            </timeBasedFileNamingAndTriggeringPolicy>
            <maxHistory>30</maxHistory>
        </rollingPolicy>
    </appender>

    <!-- 开发环境配置 -->
    <springProfile name="dev">
        <logger name="com.thaiautoparts" level="DEBUG"/>
        <logger name="org.springframework" level="INFO"/>
        <logger name="org.mybatis" level="DEBUG"/>

        <root level="DEBUG">
            <appender-ref ref="CONSOLE"/>
            <appender-ref ref="FILE"/>
            <appender-ref ref="ERROR_FILE"/>
        </root>
    </springProfile>

    <!-- 生产环境配置 -->
    <springProfile name="prod">
        <logger name="com.thaiautoparts" level="INFO"/>
        <logger name="org.springframework" level="WARN"/>
        <logger name="org.mybatis" level="WARN"/>

        <root level="INFO">
            <appender-ref ref="CONSOLE"/>
            <appender-ref ref="FILE"/>
            <appender-ref ref="ERROR_FILE"/>
        </root>
    </springProfile>

    <!-- 默认配置（无profile时） -->
    <springProfile name="default">
        <logger name="com.thaiautoparts" level="INFO"/>
        <root level="INFO">
            <appender-ref ref="CONSOLE"/>
            <appender-ref ref="FILE"/>
            <appender-ref ref="ERROR_FILE"/>
        </root>
    </springProfile>
</configuration>
